
[
    {
        "category_name": "공포/추리 소설",
        "books":
            [
                {
                    "id": 17,
                    "title": "백설공주에게 죽음을",
                    "author": "넬레 노이하우스",
                    "catchphrase": "미스터리의 본고장 유럽을 열광시킨 바로 그 소설!",
                    "update_day": 18,
                    "recommend": 973,
                    "published": 1926928395
                },

                {
                    "id": 21,
                    "title": "공포, 그 여섯 가지 이야기",
                    "author": "이용호",
                    "catchphrase": "공전의 히트를 기록한 공포 소설의 베스트셀러!",
                    "update_day": 20,
                    "recommend": 522,
                    "published": 1924959239
                }
            ]
    },

    {
        "category_name": "역사 소설",
        "books":
            [
                {
                    "id": 19,
                    "title": "발해 천년의 향기",
                    "author": "이수광",
                    "catchphrase": "대제국 발해, 그 풍운과 파란의 역사 공간",
                    "update_day": 18,
                    "recommend": 973,
                    "published": 1926928395
                },

                {
                    "id": 22,
                    "title": "데프콘 한중전쟁",
                    "author": "김경진",
                    "catchphrase": "한반도는 불타는가",
                    "update_day": 18,
                    "recommend": 973,
                    "published": 1926928395
                },

                {
                    "id": 27,
                    "title": "조선혁명 1812",
                    "author": "최동환",
                    "catchphrase": "최동환 장편소설",
                    "update_day": 20,
                    "recommend": 522,
                    "published": 1924959239
                }
            ]
    }
]